django_livewatch-0.3.0.dist-info/DESCRIPTION.rst
django_livewatch-0.3.0.dist-info/METADATA
django_livewatch-0.3.0.dist-info/metadata.json
django_livewatch-0.3.0.dist-info/RECORD
django_livewatch-0.3.0.dist-info/top_level.txt
django_livewatch-0.3.0.dist-info/WHEEL
livewatch/__init__.py
livewatch/tasks.py
livewatch/urls.py
livewatch/utils.py
livewatch/views.py
livewatch/extensions/__init__.py
livewatch/extensions/base.py
livewatch/extensions/cache.py
livewatch/extensions/celery.py
livewatch/extensions/rq.py
